ads_linguistics-2.0.9.data/scripts/compare_flare_to_dict
ads_linguistics-2.0.9.data/scripts/create_all_files
ads_linguistics-2.0.9.data/scripts/create_all_files_wo_dict
ads_linguistics-2.0.9.data/scripts/get_meta
ads_linguistics-2.0.9.data/scripts/run_clusters
ads_linguistics-2.0.9.data/scripts/update_flare_counts
linguistics/__init__.py
linguistics/analysis.py
linguistics/cluster.py
linguistics/decompose.py
linguistics/dictionary.py
linguistics/gensim_utils.py
linguistics/io.py
linguistics/normalise.py
linguistics/overlap.py
linguistics/pickle.py
linguistics/pre_process.py
linguistics/spark_time.py
linguistics/utils.py
linguistics/vectorise.py
ads_linguistics-2.0.9.dist-info/METADATA
ads_linguistics-2.0.9.dist-info/WHEEL
ads_linguistics-2.0.9.dist-info/top_level.txt
ads_linguistics-2.0.9.dist-info/RECORD
